{"name":"bamazon","version":"1.0.0","dependencies":{"dotenv":{"version":"8.1.0"},"inquirer":{"version":"7.0.0","dependencies":{"ansi-escapes":{"version":"4.2.1","dependencies":{"type-fest":{"version":"0.5.2"}}},"chalk":{"version":"2.4.2","dependencies":{"ansi-styles":{"version":"3.2.1","dependencies":{"color-convert":{"version":"1.9.3","dependencies":{"color-name":{"version":"1.1.3"}}}}},"escape-string-regexp":{"version":"1.0.5"},"supports-color":{"version":"5.5.0","dependencies":{"has-flag":{"version":"3.0.0"}}}}},"cli-cursor":{"version":"3.1.0","dependencies":{"restore-cursor":{"version":"3.1.0","dependencies":{"onetime":{"version":"5.1.0","dependencies":{"mimic-fn":{"version":"2.1.0"}}},"signal-exit":{"version":"3.0.2"}}}}},"cli-width":{"version":"2.2.0"},"external-editor":{"version":"3.1.0","dependencies":{"chardet":{"version":"0.7.0"},"iconv-lite":{"version":"0.4.24","dependencies":{"safer-buffer":{"version":"2.1.2"}}},"tmp":{"version":"0.0.33","dependencies":{"os-tmpdir":{"version":"1.0.2"}}}}},"figures":{"version":"3.0.0","dependencies":{"escape-string-regexp":{"version":"1.0.5"}}},"lodash":{"version":"4.17.15"},"mute-stream":{"version":"0.0.8"},"run-async":{"version":"2.3.0","dependencies":{"is-promise":{"version":"2.1.0"}}},"rxjs":{"version":"6.5.3","dependencies":{"tslib":{"version":"1.10.0"}}},"string-width":{"version":"4.1.0","dependencies":{"emoji-regex":{"version":"8.0.0"},"is-fullwidth-code-point":{"version":"3.0.0"},"strip-ansi":{"version":"5.2.0"}}},"strip-ansi":{"version":"5.2.0","dependencies":{"ansi-regex":{"version":"4.1.0"}}},"through":{"version":"2.3.8"}}},"mysql":{"version":"2.17.1","dependencies":{"bignumber.js":{"version":"7.2.1"},"readable-stream":{"version":"2.3.6","dependencies":{"core-util-is":{"version":"1.0.2"},"inherits":{"version":"2.0.4"},"isarray":{"version":"1.0.0"},"process-nextick-args":{"version":"2.0.1"},"safe-buffer":{"version":"5.1.2"},"string_decoder":{"version":"1.1.1","dependencies":{"safe-buffer":{"version":"5.1.2"}}},"util-deprecate":{"version":"1.0.2"}}},"safe-buffer":{"version":"5.1.2"},"sqlstring":{"version":"2.3.1"}}}}}